fast_arrow_auth/__init__.py
fast_arrow_auth/client.py
fast_arrow_auth/exceptions.py
fast_arrow_auth/util.py
fast_arrow_auth/version.py
fast_arrow_auth/resources/__init__.py
fast_arrow_auth/resources/account.py
fast_arrow_auth/resources/user.py
fast_arrow_auth/ssl_certs/certs.pem
fast_arrow_auth-0.0.4.dist-info/LICENSE
fast_arrow_auth-0.0.4.dist-info/METADATA
fast_arrow_auth-0.0.4.dist-info/WHEEL
fast_arrow_auth-0.0.4.dist-info/top_level.txt
fast_arrow_auth-0.0.4.dist-info/RECORD
