Metadata-Version: 2.1
Name: fast-arrow-auth
Version: 0.0.4
Summary: A library to handle authentication with Robinhood's API
Home-page: https://github.com/westonplatter/fast_arrow_auth/
Author: Weston Platter
Author-email: westonplatter@gmail.com
License: MIT License
Project-URL: Issue Tracker, https://github.com/westonplatter/fast_arrow_auth/issues
Project-URL: Source Code, https://github.com/westonplatter/fast_arrow_auth
Platform: UNKNOWN
Requires-Python: >=3.5
Requires-Dist: datetime
Requires-Dist: deprecation
Requires-Dist: pathlib2
Requires-Dist: requests (>=2.20.0)
Requires-Dist: yarl
Requires-Dist: urllib3 (>=1.24.2)
